molgenis_emx2_ontomanager/OntologyManager.py
molgenis_emx2_ontomanager/__init__.py
molgenis_emx2_ontomanager/__main__.py
molgenis_emx2_ontomanager/constants.py
molgenis_emx2_ontomanager/exceptions.py
molgenis_emx2_ontomanager/graphql_queries.py
molgenis_emx2_ontomanager/utils.py
molgenis_emx2_ontomanager-0.2.17.dist-info/METADATA
molgenis_emx2_ontomanager-0.2.17.dist-info/WHEEL
molgenis_emx2_ontomanager-0.2.17.dist-info/top_level.txt
molgenis_emx2_ontomanager-0.2.17.dist-info/RECORD
