Metadata-Version: 2.1
Name: molgenis-emx2-ontomanager
Version: 0.2.17
Summary: Tool to manage catalogue ontologies on Molgenis EMX2 servers.
Project-URL: Homepage, https://github.com/molgenis/molgenis-emx2
Project-URL: Bug Tracker, https://github.com/molgenis/molgenis-emx2/issues
Classifier: Programming Language :: Python :: 3
Classifier: License :: OSI Approved :: GNU Lesser General Public License v3 (LGPLv3)
Classifier: Operating System :: OS Independent
Requires-Python: >=3.7
Requires-Dist: requests ~=2.31.0
Requires-Dist: molgenis-emx2-pyclient ~=8.213.13
Requires-Dist: python-dotenv ==1.0.0
Requires-Dist: pandas ~=2.0.3
Requires-Dist: numpy ~=1.25.1
Requires-Dist: tqdm ~=4.66.1
